imodulator/ChargeSimulator.py
imodulator/Config.py
imodulator/ElectroOpticalModel.py
imodulator/ElectroOpticalSimulator.py
imodulator/OpticalSimulator.py
imodulator/PhotonicDevice.py
imodulator/PhotonicPolygon.py
imodulator/RFSimulator.py
imodulator/__init__.py
imodulator/config_template.yaml
imodulator-1.0.2.dist-info/METADATA
imodulator-1.0.2.dist-info/WHEEL
imodulator-1.0.2.dist-info/licenses/LICENSE
imodulator-1.0.2.dist-info/RECORD
