Metadata-Version: 2.4
Name: imodulator
Version: 1.0.2
Summary: An all-in-one photonic electro-optic modulator design tool with complete modularity providing consistent optical mode solving, charge transport simulations, RF mode solving and transmission line analysis for arbitrary materials and cross sections.
Project-URL: Homepage, https://github.com/duarte-jfs/Imodulator
Project-URL: Documentation, https://imodulator.readthedocs.io/en/latest/
Project-URL: Repository, https://github.com/duarte-jfs/Imodulator
Author-email: Duarte Silva <d.j.fernandes.da.silva@tue.nl>, Ali Kaan Sünnetçioğlu <a.k.sunnetcioglu@tue.nl>
Maintainer-email: Duarte Silva <d.j.fernandes.da.silva@tue.nl>, Ali Kaan Sünnetçioğlu <a.k.sunnetcioglu@tue.nl>
License:                     GNU AFFERO GENERAL PUBLIC LICENSE
License-File: LICENSE
Keywords: charge transport simulation,electro-optic interaction,electro-optic modulators,integrated photonics,optical mode solver,photonics simulation,rf mode solver
Classifier: Programming Language :: Python :: 3
Requires-Python: >=3.10
Requires-Dist: matplotlib==3.9.0
Requires-Dist: nextnanopy>=1.0.1
Requires-Dist: numpy>=2.0.0
Requires-Dist: openbandparams>=1.0
Requires-Dist: pandas==2.3.0
Requires-Dist: pint>=0.24
Requires-Dist: pygmsh>=7.1.17
Requires-Dist: pyyaml==6.0.2
Requires-Dist: scikit-fem>=11.0.0
Requires-Dist: scipy==1.13.1
Requires-Dist: shapely==2.0.4
Requires-Dist: solcore>=5.10.1
